ml_pipeline/__init__.py
ml_pipeline/app.py
ml_pipeline/eda.py
ml_pipeline/launcher.py
ml_pipeline/model.py
ml_pipeline/preprocessing.py
ml_pipeline_dashboard-0.1.14.dist-info/LICENSE
ml_pipeline_dashboard-0.1.14.dist-info/METADATA
ml_pipeline_dashboard-0.1.14.dist-info/WHEEL
ml_pipeline_dashboard-0.1.14.dist-info/entry_points.txt
ml_pipeline_dashboard-0.1.14.dist-info/top_level.txt
ml_pipeline_dashboard-0.1.14.dist-info/RECORD
